ms_graph_client/__init__.py
ms_graph_client/__init__.pyi
ms_graph_client/exceptions.py
ms_graph_client/exceptions.pyi
ms_graph_client/graph_api_config.py
ms_graph_client/graph_api_config.pyi
ms_graph_client/graph_api_crud_base.py
ms_graph_client/graph_api_crud_base.pyi
ms_graph_client/py.typed
ms_graph_client/services/__init__.py
ms_graph_client/services/__init__.pyi
ms_graph_client/services/applications.py
ms_graph_client/services/applications.pyi
ms_graph_client/services/generator.py
ms_graph_client/services/generator.pyi
ms_graph_client/services/graph_api.py
ms_graph_client/services/graph_api.pyi
ms_graph_client/services/groups.py
ms_graph_client/services/groups.pyi
ms_graph_client/services/users.py
ms_graph_client/services/users.pyi
ms_graph_client/services.pyi
ms_graph_client/services_cache/__init__.py
ms_graph_client/services_cache/__init__.pyi
ms_graph_client/services_cache/applications.py
ms_graph_client/services_cache/applications.pyi
ms_graph_client/services_cache/graph_api.py
ms_graph_client/services_cache/graph_api.pyi
ms_graph_client/services_cache/groups.py
ms_graph_client/services_cache/groups.pyi
ms_graph_client/services_cache/users.py
ms_graph_client/services_cache/users.pyi
ms_graph_client/services_cache.pyi
ms_graph_client-0.2.1.dist-info/METADATA
ms_graph_client-0.2.1.dist-info/WHEEL
ms_graph_client-0.2.1.dist-info/RECORD
