Metadata-Version: 2.3
Name: ms_graph_client
Version: 0.2.1
Summary: Provides a python wrapper around the Microsoft Graph API.  Current SDKs from Microsoft are in Preview mode.
License: MIT
Author: Nick Carpenter
Requires-Python: >=3.8.1,<4.0.0
Classifier: License :: OSI Approved :: MIT License
Classifier: Programming Language :: Python :: 3
Classifier: Programming Language :: Python :: 3.9
Classifier: Programming Language :: Python :: 3.10
Classifier: Programming Language :: Python :: 3.11
Classifier: Programming Language :: Python :: 3.12
Classifier: Programming Language :: Python :: 3.13
Requires-Dist: cachetools (>=5.0.0,<6.0.0)
Requires-Dist: requests (>=2.25.0,<3.0.0)
Project-URL: Homepage, https://github.com/carpnick/ms_graph_client
